nebula/.nebulaignore
nebula/__init__.py
nebula/_version.py
nebula/agent.py
nebula/artifacts.py
nebula/context.py
nebula/engine.py
nebula/exceptions.py
nebula/filesystems.py
nebula/flow_runs.py
nebula/flows.py
nebula/futures.py
nebula/manifests.py
nebula/plugins.py
nebula/profiles.toml
nebula/py.typed
nebula/results.py
nebula/serializers.py
nebula/settings.py
nebula/states.py
nebula/task_engine.py
nebula/task_runners.py
nebula/task_server.py
nebula/tasks.py
nebula/variables.py
nebula/_internal/__init__.py
nebula/_internal/_logging.py
nebula/_internal/pytz.py
nebula/_internal/compatibility/__init__.py
nebula/_internal/compatibility/deprecated.py
nebula/_internal/compatibility/experimental.py
nebula/_internal/concurrency/__init__.py
nebula/_internal/concurrency/api.py
nebula/_internal/concurrency/calls.py
nebula/_internal/concurrency/cancellation.py
nebula/_internal/concurrency/event_loop.py
nebula/_internal/concurrency/inspection.py
nebula/_internal/concurrency/primitives.py
nebula/_internal/concurrency/services.py
nebula/_internal/concurrency/threads.py
nebula/_internal/concurrency/waiters.py
nebula/_internal/pydantic/__init__.py
nebula/_internal/pydantic/_compat.py
nebula/_internal/pydantic/schemas.py
nebula/_internal/pydantic/v2_schema.py
nebula/_internal/pydantic/v2_validated_func.py
nebula/_internal/pydantic/annotations/__init__.py
nebula/_internal/pydantic/annotations/pendulum.py
nebula/_internal/schemas/__init__.py
nebula/_internal/schemas/bases.py
nebula/_internal/schemas/fields.py
nebula/_internal/schemas/serializers.py
nebula/_internal/schemas/transformations.py
nebula/_internal/schemas/validators.py
nebula/_vendor/__init__.py
nebula/_vendor/fastapi/__init__.py
nebula/_vendor/fastapi/applications.py
nebula/_vendor/fastapi/background.py
nebula/_vendor/fastapi/concurrency.py
nebula/_vendor/fastapi/datastructures.py
nebula/_vendor/fastapi/encoders.py
nebula/_vendor/fastapi/exception_handlers.py
nebula/_vendor/fastapi/exceptions.py
nebulaconsole-1.0.0.dist-info/LICENSE
nebulaconsole-1.0.0.dist-info/METADATA
nebulaconsole-1.0.0.dist-info/WHEEL
nebulaconsole-1.0.0.dist-info/entry_points.txt
nebulaconsole-1.0.0.dist-info/top_level.txt
nebulaconsole-1.0.0.dist-info/RECORD
