Metadata-Version: 2.1
Name: nebulaconsole
Version: 1.0.0
Summary: Workflow orchestration and management.
Home-page: https://www.nebula.io
Author: Kozmoai, Inc.
Author-email: contact@kozmoai.org
Project-URL: Changelog, https://github.com/kozmoai/nebula/blob/main/RELEASE-NOTES.md
Project-URL: Documentation, https://docs.nebula.io
Project-URL: Source, https://github.com/kozmoai/nebula
Project-URL: Tracker, https://github.com/kozmoai/nebula/issues
Classifier: Natural Language :: English
Classifier: Intended Audience :: Developers
Classifier: Intended Audience :: System Administrators
Classifier: License :: OSI Approved :: Apache Software License
Classifier: Programming Language :: Python :: 3 :: Only
Classifier: Programming Language :: Python :: 3.8
Classifier: Programming Language :: Python :: 3.9
Classifier: Programming Language :: Python :: 3.10
Classifier: Programming Language :: Python :: 3.11
Classifier: Programming Language :: Python :: 3.12
Classifier: Topic :: Software Development :: Libraries
Requires-Python: >=3.8
License-File: LICENSE
Requires-Dist: aiosqlite >=0.17.0
Requires-Dist: alembic <2.0.0,>=1.7.5
Requires-Dist: apprise <2.0.0,>=1.1.0
Requires-Dist: asyncpg >=0.23
Requires-Dist: click <8.2,>=8.0
Requires-Dist: cryptography >=36.0.1
Requires-Dist: dateparser <2.0.0,>=1.1.1
Requires-Dist: docker <7.0,>=4.0
Requires-Dist: graphviz >=0.20.1
Requires-Dist: griffe >=0.20.0
Requires-Dist: jinja2 <4.0.0,>=3.0.0
Requires-Dist: kubernetes <30.0.0,>=24.2.0
Requires-Dist: pytz <2025,>=2021.1
Requires-Dist: readchar <5.0.0,>=4.0.0
Requires-Dist: sqlalchemy[asyncio] !=1.4.33,<3.0.0,>=1.4.22
Requires-Dist: typer >=0.4.2
Requires-Dist: anyio <4.0.0,>=3.7.1
Requires-Dist: asgi-lifespan <3.0,>=1.0
Requires-Dist: cachetools <6.0,>=5.3
Requires-Dist: cloudpickle <4.0,>=2.0
Requires-Dist: coolname <3.0.0,>=1.0.4
Requires-Dist: croniter <3.0.0,>=1.0.12
Requires-Dist: fsspec >=2022.5.0
Requires-Dist: httpcore <2.0.0,>=0.15.0
Requires-Dist: httpx[http2] !=0.23.2,>=0.23
Requires-Dist: jsonpatch <2.0,>=1.32
Requires-Dist: jsonschema <5.0.0,>=3.2.0
Requires-Dist: orjson <4.0,>=3.7
Requires-Dist: packaging <24.3,>=21.3
Requires-Dist: pathspec >=0.8.0
Requires-Dist: pydantic[email] !=2.0.0,!=2.0.1,!=2.1.0,<3.0.0,>=1.10.0
Requires-Dist: python-dateutil <3.0.0,>=2.8.2
Requires-Dist: python-slugify <9.0,>=5.0
Requires-Dist: pyyaml <7.0.0,>=5.4.1
Requires-Dist: rfc3339-validator <0.2.0,>=0.1.4
Requires-Dist: rich <14.0,>=11.0
Requires-Dist: ruamel.yaml >=0.17.0
Requires-Dist: sniffio <2.0.0,>=1.3.0
Requires-Dist: toml >=0.10.0
Requires-Dist: typing-extensions <5.0.0,>=4.5.0
Requires-Dist: ujson <6.0.0,>=5.8.0
Requires-Dist: uvicorn >=0.14.0
Requires-Dist: websockets <13.0,>=10.4
Requires-Dist: itsdangerous
Requires-Dist: python-multipart >=0.0.7
Requires-Dist: importlib-metadata >=4.4 ; python_version < "3.10"
Requires-Dist: pendulum <3.0 ; python_version < "3.12"
Requires-Dist: pendulum <4,>=3.0.0 ; python_version >= "3.12"
Provides-Extra: dev
Requires-Dist: ruff ; extra == 'dev'
Requires-Dist: cairosvg ; extra == 'dev'
Requires-Dist: codespell >=2.2.6 ; extra == 'dev'
Requires-Dist: ddtrace ; extra == 'dev'
Requires-Dist: jinja2 ; extra == 'dev'
Requires-Dist: mkdocs ; extra == 'dev'
Requires-Dist: mkdocs-gen-files ; extra == 'dev'
Requires-Dist: mkdocs-material ; extra == 'dev'
Requires-Dist: mkdocstrings-python ; extra == 'dev'
Requires-Dist: mike ; extra == 'dev'
Requires-Dist: moto >=5 ; extra == 'dev'
Requires-Dist: mypy ; extra == 'dev'
Requires-Dist: numpy ; extra == 'dev'
Requires-Dist: pillow ; extra == 'dev'
Requires-Dist: pre-commit ; extra == 'dev'
Requires-Dist: pluggy >=1.4.0 ; extra == 'dev'
Requires-Dist: pytest <8,>7 ; extra == 'dev'
Requires-Dist: pytest-asyncio !=0.22.0,<0.23.0,>=0.18.2 ; extra == 'dev'
Requires-Dist: pytest-cov ; extra == 'dev'
Requires-Dist: pytest-benchmark ; extra == 'dev'
Requires-Dist: pytest-env ; extra == 'dev'
Requires-Dist: pytest-flakefinder ; extra == 'dev'
Requires-Dist: pytest-timeout ; extra == 'dev'
Requires-Dist: pytest-xdist <3.4.0 ; extra == 'dev'
Requires-Dist: pytkdocs >=0.14.2 ; extra == 'dev'
Requires-Dist: pyyaml ; extra == 'dev'
Requires-Dist: requests ; extra == 'dev'
Requires-Dist: virtualenv ; extra == 'dev'
Requires-Dist: watchfiles ; extra == 'dev'
Requires-Dist: respx ; extra == 'dev'
Requires-Dist: mock ; (python_version < "3.8") and extra == 'dev'
Requires-Dist: setuptools !=60.9.0 ; (python_version < "3.8") and extra == 'dev'
Requires-Dist: ipython ==8.12.* ; (python_version == "3.8") and extra == 'dev'
Requires-Dist: ipython ; (python_version > "3.8") and extra == 'dev'
